MANIFEST.in
README.txt
TODO.txt
setup.py
docs/HISTORY.txt
docs/INSTALL.txt
plone/__init__.py
plone.app.themeeditor.egg-info/PKG-INFO
plone.app.themeeditor.egg-info/SOURCES.txt
plone.app.themeeditor.egg-info/dependency_links.txt
plone.app.themeeditor.egg-info/entry_points.txt
plone.app.themeeditor.egg-info/namespace_packages.txt
plone.app.themeeditor.egg-info/not-zip-safe
plone.app.themeeditor.egg-info/requires.txt
plone.app.themeeditor.egg-info/top_level.txt
plone/app/__init__.py
plone/app/themeeditor/__init__.py
plone/app/themeeditor/cmf.py
plone/app/themeeditor/configure.zcml
plone/app/themeeditor/interfaces.py
plone/app/themeeditor/portlet.py
plone/app/themeeditor/retriever.py
plone/app/themeeditor/setuphandlers.py
plone/app/themeeditor/utils.py
plone/app/themeeditor/viewlet.py
plone/app/themeeditor/write_utils.py
plone/app/themeeditor/zopeview.py
plone/app/themeeditor/browser/__init__.py
plone/app/themeeditor/browser/configure.zcml
plone/app/themeeditor/browser/console.pt
plone/app/themeeditor/browser/console.py
plone/app/themeeditor/browser/export.py
plone/app/themeeditor/browser/export_form.pt
plone/app/themeeditor/browser/failsafe_main_template.pt
plone/app/themeeditor/browser/layers.pt
plone/app/themeeditor/browser/validator.py
plone/app/themeeditor/browser/resources/icon.png
plone/app/themeeditor/browser/resources/sample.png
plone/app/themeeditor/browser/resources/style.css
plone/app/themeeditor/browser/resources/themeeditor.js
plone/app/themeeditor/locales/plone.app.themeeditor.pot
plone/app/themeeditor/locales/en/LC_MESSAGES/plone.app.themeeditor.po
plone/app/themeeditor/locales/es/LC_MESSAGES/plone.app.themeeditor.po
plone/app/themeeditor/locales/fr/LC_MESSAGES/plone.app.themeeditor.po
plone/app/themeeditor/profiles/default/controlpanel.xml
plone/app/themeeditor/profiles/default/metadata.xml
plone/app/themeeditor/profiles/uninstall/import_steps.xml
plone/app/themeeditor/profiles/uninstall/plone.app.themeeditor-uninstall.txt
plone/app/themeeditor/templates/browser_configure.zcml.tmpl
plone/app/themeeditor/templates/jbot.zcml.tmpl
plone/app/themeeditor/templates/metadata.xml.tmpl
plone/app/themeeditor/templates/profiles.zcml.tmpl
plone/app/themeeditor/templates/setup.py.tmpl
plone/app/themeeditor/templates/skins.xml.tmpl
plone/app/themeeditor/templates/skins.zcml.tmpl
plone/app/themeeditor/templates/viewlets.xml.tmpl
