Metadata-Version: 1.0
Name: plone.app.themeeditor
Version: 1.0a8
Summary: Theme Editor for Plone, Customize your theme resources
Home-page: UNKNOWN
Author: David Glick
Author-email: davidglick@groundwire.org
License: GPL
Keywords: theme editor customization plone
Platform: UNKNOWN
Classifier: Programming Language :: Python
